djchoices/__init__.py
djchoices/choices.py
djchoices/management/__init__.py
djchoices/management/commands/__init__.py
djchoices/management/commands/generate_native_django_choices.py
djchoices/tests/__init__.py
djchoices/tests/test_choices.py
djchoices/tests/test_native_choices.py
djchoices/tests/test_private_api.py
django_choices-2.0.0.dist-info/LICENSE
django_choices-2.0.0.dist-info/METADATA
django_choices-2.0.0.dist-info/WHEEL
django_choices-2.0.0.dist-info/top_level.txt
django_choices-2.0.0.dist-info/RECORD
