Metadata-Version: 2.1
Name: django-choices
Version: 2.0.0
Summary: Sanity for the django choices functionality.
Home-page: https://github.com/bigjason/django-choices
Author: Jason Webb
Author-email: bigjasonwebb@gmail.com,sergeimaertens@gmail.com
License: MIT
Classifier: Development Status :: 5 - Production/Stable
Classifier: Operating System :: OS Independent
Classifier: License :: OSI Approved :: MIT License
Classifier: Intended Audience :: Developers
Classifier: Framework :: Django
Classifier: Framework :: Django :: 3.2
Classifier: Framework :: Django :: 4.1
Classifier: Framework :: Django :: 4.2
Classifier: Programming Language :: Python :: 3.8
Classifier: Programming Language :: Python :: 3.9
Classifier: Programming Language :: Python :: 3.10
Classifier: Programming Language :: Python :: 3.11
Classifier: Programming Language :: Python :: Implementation :: PyPy
License-File: LICENSE
